jsoml/__init__.py
jsoml/__main__.py
jsoml/decoder.py
jsoml/encoder.py
jsoml/py.typed
jsoml-0.4.1.dist-info/LICENSE
jsoml-0.4.1.dist-info/METADATA
jsoml-0.4.1.dist-info/WHEEL
jsoml-0.4.1.dist-info/entry_points.txt
jsoml-0.4.1.dist-info/top_level.txt
jsoml-0.4.1.dist-info/RECORD
