Metadata-Version: 2.2
Name: jsoml
Version: 0.4.1
Summary: JavaScript Object Markup Language
Home-page: https://gitlab.com/castedo/jsoml
Author: Castedo Ellerman
Author-email: castedo@castedo.com
License: MIT License
Classifier: Development Status :: 4 - Beta
Classifier: License :: OSI Approved :: MIT License
Classifier: Programming Language :: Python :: 3
Classifier: Operating System :: POSIX
Classifier: Topic :: Text Processing :: Markup :: XML
Requires-Python: >=3.9
License-File: LICENSE
Requires-Dist: lxml
